plausipy/__init__.py
plausipy/cli.py
plausipy/error.py
plausipy/info.py
plausipy/paths.py
plausipy/plausipy.py
plausipy/user.py
plausipy/utils.py
plausipy-0.6.0.dist-info/METADATA
plausipy-0.6.0.dist-info/WHEEL
plausipy-0.6.0.dist-info/entry_points.txt
plausipy-0.6.0.dist-info/licenses/LICENSE
plausipy-0.6.0.dist-info/RECORD
