Metadata-Version: 2.4
Name: plausipy
Version: 0.6.0
Summary: Plausipy is a Python package that provides insightful usage information while prioritizing user privacy. It empowers users by giving them control over their data and emphasizes transparency to build trust between developers and users. Ideal for applications that aim to balance analytics with responsible data management, Plausipy promotes ethical data handling as the standard.
Author-email: Leonard Nürnberg <leonard.nuernberg@moontec.de>
License-File: LICENSE
Classifier: Development Status :: 3 - Alpha
Classifier: Intended Audience :: Developers
Classifier: Intended Audience :: End Users/Desktop
Classifier: Intended Audience :: Science/Research
Classifier: License :: OSI Approved :: MIT License
Classifier: Natural Language :: English
Classifier: Topic :: Software Development :: Libraries
Requires-Python: >=3.10
Requires-Dist: prompt-toolkit>=3.0.50
Requires-Dist: psutil>=6.1.1
Requires-Dist: qrcode>=8.0
Requires-Dist: requests>=2.32.3
Requires-Dist: safe-exit>=0.1.2
Requires-Dist: tabulate>=0.9.0
